how_its_made.py
how_its_made-1.2.dist-info/LICENSE
how_its_made-1.2.dist-info/METADATA
how_its_made-1.2.dist-info/WHEEL
how_its_made-1.2.dist-info/top_level.txt
how_its_made-1.2.dist-info/RECORD
