Metadata-Version: 2.1
Name: how-its-made
Version: 1.2
Summary: Generates how it's made titles
Author: Callum Evans
License: UNKNOWN
Platform: UNKNOWN
Classifier: Programming Language :: Python :: 3
Classifier: Operating System :: OS Independent
Requires-Python: >=3.6
License-File: LICENSE
Requires-Dist: pyttsx3 (>=2.90)
